{
  "schemaVersion": 1,
  "question": "In golf, what happens if you swing at the ball and miss, commonly known as an 'air shot'?*",
  "type": "multiple_choice",
  "choices": [
    {
      "id": "a",
      "text": "It counts as a stroke, and you play the ball from where it lies."
    },
    {
      "id": "b",
      "text": "You can re-try without penalty since the ball was not struck."
    },
    {
      "id": "c",
      "text": "If the ball moves but stays within the teeing area marked by the tee markers you can tee the ball back up before hitting it again"
    },
    {
      "id": "d",
      "text": "You can replace the ball on a tee without counting the miss as a stroke."
    }
  ],
  "correctAnswer": null,
  "explanation": "In golf, an 'air shot' (a swing and miss) is counted as a stroke. When you make a stroke and miss the ball, it counts as one stroke under the rules of golf.",
  "imageAlt": "Screenshot 2024-01-22 110415"
}